flagser/__init__.py
flagser/flagser.py
flagser-2.4.dist-info/LICENCE
flagser-2.4.dist-info/METADATA
flagser-2.4.dist-info/WHEEL
flagser-2.4.dist-info/top_level.txt
flagser-2.4.dist-info/RECORD
