Metadata-Version: 2.1
Name: flagser
Version: 2.4
Summary: Flag manager
Home-page: https://github.com/spynetS/flagser
Author: Alfred Roos
Author-email: alfred@stensatter.se
Classifier: Programming Language :: Python :: 3
Classifier: License :: OSI Approved :: MIT License
Classifier: Operating System :: OS Independent
License-File: LICENCE
